comparators/Comparator.py
comparators/PearsonsCorrelation.py
comparators/__init__.py
comparison_tools/.jukit/.jukit_info.json
comparison_tools/.jukit/temp_outhist.json
comparison_tools/PairwiseCompare.py
comparison_tools/PairwiseCompare.py.bac
comparison_tools/PairwiseCompareManager.py
comparison_tools/__init__.py
pairwise_compare-0.1.3.dist-info/LICENSE
pairwise_compare-0.1.3.dist-info/METADATA
pairwise_compare-0.1.3.dist-info/WHEEL
pairwise_compare-0.1.3.dist-info/RECORD
