Metadata-Version: 2.3
Name: pairwise-compare
Version: 0.1.3
Summary: Allows the user to compare groups of data specified in a tidy pandas dataframe with ease.
License: BSD 3-Clause
Author: Cameron Mattson
Author-email: mattsoncameron1@gmail.com
Requires-Python: >=3.10,<3.13
Classifier: License :: Other/Proprietary License
Classifier: Programming Language :: Python :: 3
Classifier: Programming Language :: Python :: 3.10
Classifier: Programming Language :: Python :: 3.11
Classifier: Programming Language :: Python :: 3.12
Requires-Dist: numpy (>=2.1.3,<3.0.0)
Requires-Dist: pandas (>=2.2.3,<3.0.0)
Requires-Dist: pathlib2 (>=2.3.7.post1,<3.0.0)
Requires-Dist: pyarrow (>=18.0.0,<19.0.0)
Requires-Dist: setuptools (>=14.0)
